{
  "last_updated": "2026-01-20T18:14:34.094813+00:00",
  "totals": {
    "total_pulls": 1296,
    "total_stars": 0
  },
  "repositories": {
    "neonvariant/dumpsterr": {
      "pull_count": 884,
      "star_count": 0,
      "description": "Safely empties your Plex trash, verifying file availability before doing so.",
      "last_updated": "2026-01-20T18:14:08.347891Z"
    },
    "neonvariant/mythicmate": {
      "pull_count": 412,
      "star_count": 0,
      "description": "A D&D Discord bot that facilitates dice rolling and rules referencing.",
      "last_updated": "2026-01-14T04:07:08.811234Z"
    }
  }
}